suraj_nagaje/__init__.py
suraj_nagaje/requirements.txt
suraj_nagaje/suraj_demo.py
suraj_nagaje-0.1.0.dist-info/METADATA
suraj_nagaje-0.1.0.dist-info/WHEEL
suraj_nagaje-0.1.0.dist-info/RECORD
