Metadata-Version: 2.1
Name: suraj_nagaje
Version: 0.1.0
Summary: 
Author: Your Name
Author-email: you@example.com
Requires-Python: >=3.10,<4.0
Classifier: Programming Language :: Python :: 3
Classifier: Programming Language :: Python :: 3.10
Classifier: Programming Language :: Python :: 3.11
Classifier: Programming Language :: Python :: 3.12
Classifier: Programming Language :: Python :: 3.13
Requires-Dist: beautifulsoup4 (>=4.12.3,<5.0.0)
Requires-Dist: pytest (>=8.3.4,<9.0.0)
Requires-Dist: requests (>=2.32.3,<3.0.0)
